i2ptunnel-0.1.3.dist-info/METADATA
i2ptunnel-0.1.3.dist-info/WHEEL
i2ptunnel-0.1.3.dist-info/entry_points.txt
i2ptunnel-0.1.3.dist-info/licenses/LICENSE
i2ptunnel/__init__.py
i2ptunnel/i2ptunnel.cp312-win_amd64.pyd
i2ptunnel-0.1.3.dist-info/RECORD
