Metadata-Version: 2.4
Name: i2ptunnel
Version: 0.1.3
Classifier: Development Status :: 4 - Beta
Classifier: License :: OSI Approved :: MIT License
Classifier: Programming Language :: Rust
Classifier: Programming Language :: Python :: Implementation :: CPython
Classifier: Programming Language :: Python :: Implementation :: PyPy
Classifier: Programming Language :: Python :: 3
Classifier: Programming Language :: Python :: 3.8
Classifier: Programming Language :: Python :: 3.9
Classifier: Programming Language :: Python :: 3.10
Classifier: Programming Language :: Python :: 3.11
Classifier: Programming Language :: Python :: 3.12
Classifier: Topic :: Internet :: WWW/HTTP :: HTTP Servers
Classifier: Topic :: Internet :: Proxy Servers
Classifier: Topic :: System :: Networking
Classifier: Topic :: Security
Requires-Dist: requests>=2.25.0
Requires-Dist: tqdm>=4.65.0
License-File: LICENSE
Summary: I2P Proxy Tunnel with Python decorator support
Keywords: i2p,proxy,tunnel,anonymity,privacy,networking
Home-Page: https://github.com/Krabbens/i2ptunnel
Author-email: quo <dot@quose.cat>
License: MIT
Requires-Python: >=3.8
Project-URL: Homepage, https://github.com/Krabbens/i2ptunnel
Project-URL: Repository, https://github.com/Krabbens/i2ptunnel
Project-URL: Issues, https://github.com/Krabbens/i2ptunnel/issues
Project-URL: Documentation, https://github.com/Krabbens/i2ptunnel#readme
